smart_env/__init__.py
smart_env/decoders.py
smart_env/env.py
smart_env/exceptions.py
smart_env/iterator.py
smart_env/util.py
smart_env-1.0.5.dist-info/LICENSE
smart_env-1.0.5.dist-info/METADATA
smart_env-1.0.5.dist-info/WHEEL
smart_env-1.0.5.dist-info/top_level.txt
smart_env-1.0.5.dist-info/RECORD
