Metadata-Version: 2.1
Name: smart-env
Version: 1.0.5
Summary: Smart Environment Wrapper Library
Home-page: https://github.com/atcode-space/smart-env
Author: Oleksandr Sokolov
Author-email: volokolek@gmail.com
License: UNKNOWN
Project-URL: Source, https://github.com/atcode-space/smart-env/
Keywords: env environ smartenv
Platform: UNKNOWN
Classifier: Development Status :: 5 - Production/Stable
Classifier: Intended Audience :: Developers
Classifier: Topic :: Software Development :: Libraries :: Python Modules
Classifier: License :: OSI Approved :: MIT License
Classifier: Programming Language :: Python :: 2.7
Classifier: Programming Language :: Python :: 3
Classifier: Programming Language :: Python :: 3.5
Classifier: Programming Language :: Python :: 3.6
Classifier: Programming Language :: Python :: 3.7
Classifier: Programming Language :: Python :: 3.8
Classifier: Programming Language :: Python :: 3.9
Classifier: Programming Language :: Python :: 3.10
Classifier: Programming Language :: Python :: 3.11
Requires-Python: >=2.7.*, !=3.0.*, !=3.1.*, !=3.2.*, !=3.3.*, !=3.4.*, <3.12
License-File: LICENSE
Requires-Dist: six (>=1.14.0)
